stackit/objectstorage/__init__.py
stackit/objectstorage/api/__init__.py
stackit/objectstorage/api/default_api.py
stackit/objectstorage/api_client.py
stackit/objectstorage/api_response.py
stackit/objectstorage/configuration.py
stackit/objectstorage/exceptions.py
stackit/objectstorage/models/__init__.py
stackit/objectstorage/models/access_key.py
stackit/objectstorage/models/bucket.py
stackit/objectstorage/models/create_access_key_payload.py
stackit/objectstorage/models/create_access_key_response.py
stackit/objectstorage/models/create_bucket_response.py
stackit/objectstorage/models/create_credentials_group_payload.py
stackit/objectstorage/models/create_credentials_group_response.py
stackit/objectstorage/models/credentials_group.py
stackit/objectstorage/models/delete_access_key_response.py
stackit/objectstorage/models/delete_bucket_response.py
stackit/objectstorage/models/delete_credentials_group_response.py
stackit/objectstorage/models/detailed_error.py
stackit/objectstorage/models/error_message.py
stackit/objectstorage/models/get_bucket_response.py
stackit/objectstorage/models/http_validation_error.py
stackit/objectstorage/models/list_access_keys_response.py
stackit/objectstorage/models/list_buckets_response.py
stackit/objectstorage/models/list_credentials_groups_response.py
stackit/objectstorage/models/location_inner.py
stackit/objectstorage/models/project_scope.py
stackit/objectstorage/models/project_status.py
stackit/objectstorage/models/validation_error.py
stackit/objectstorage/py.typed
stackit/objectstorage/rest.py
stackit_objectstorage-1.2.1.dist-info/METADATA
stackit_objectstorage-1.2.1.dist-info/WHEEL
stackit_objectstorage-1.2.1.dist-info/licenses/LICENSE.md
stackit_objectstorage-1.2.1.dist-info/licenses/NOTICE.txt
stackit_objectstorage-1.2.1.dist-info/RECORD
